plotsignif/__init__.py
plotsignif/core.py
plotsignif-0.1.0.dist-info/licenses/LICENSE
plotsignif-0.1.0.dist-info/METADATA
plotsignif-0.1.0.dist-info/WHEEL
plotsignif-0.1.0.dist-info/top_level.txt
plotsignif-0.1.0.dist-info/RECORD
